aliver/__init__.py
aliver/__main__.py
aliver-1.0.4.dist-info/METADATA
aliver-1.0.4.dist-info/WHEEL
aliver-1.0.4.dist-info/entry_points.txt
aliver-1.0.4.dist-info/top_level.txt
aliver-1.0.4.dist-info/RECORD
