Metadata-Version: 2.1
Name: aliver
Version: 1.0.4
Summary: A module made for repl.it users
Home-page: https://github.com/alshahriah/aliver
Author: Al-Shahriah
Author-email: alshahriah2007@gmail.com
License: MIT
Platform: UNKNOWN
Classifier: License :: OSI Approved :: MIT License
Classifier: Programming Language :: Python :: 3
Classifier: Programming Language :: Python :: 3.7
Requires-Dist: flask
